rustic_ai/playwright/__init__.py
rustic_ai/playwright/agent.py
rusticai_playwright-1.0.0.dist-info/METADATA
rusticai_playwright-1.0.0.dist-info/WHEEL
rusticai_playwright-1.0.0.dist-info/RECORD
