Metadata-Version: 2.4
Name: rusticai-playwright
Version: 1.0.0
Summary: Rustic AI module for scraping using playwright
License-Expression: Apache-2.0
Author: Dragonscale Industries Inc.
Author-email: dev@dragonscale.ai
Requires-Python: >=3.12,<3.13
Classifier: Programming Language :: Python :: 3
Classifier: Programming Language :: Python :: 3.12
Provides-Extra: test
Requires-Dist: install-playwright (>=0.1.1,<0.2.0)
Requires-Dist: markdownify (>=1.1.0,<2.0.0)
Requires-Dist: playwright (>=1.51.0,<2.0.0)
Requires-Dist: rusticai-core (>=1.0.0,<1.1.0)
Project-URL: Homepage, https://www.rustic.ai/
Project-URL: Repository, https://github.com/rustic-ai/rustic-ai
Project-URL: Rustic AI Core, https://pypi.org/project/rusticai-core/
